c.py
urcalc-0.2.0.dist-info/RECORD
urcalc-0.2.0.dist-info/METADATA
urcalc-0.2.0.dist-info/pydist.json
urcalc-0.2.0.dist-info/DESCRIPTION.rst
urcalc-0.2.0.dist-info/WHEEL
urcalc-0.2.0.data/scripts/c
