Metadata-Version: 2.0
Name: urcalc
Version: 0.2.0
Summary: Simple calculator in terminal using Urwid
Home-page: http://bitbucket.org/livibetter/c
Author: Yu-Jie Lin
Author-email: livibetter@gmail.com
License: MIT License
Platform: UNKNOWN
Classifier: Development Status :: 3 - Alpha
Classifier: Environment :: Console
Classifier: Environment :: Console :: Curses
Classifier: Intended Audience :: End Users/Desktop
Classifier: License :: OSI Approved :: MIT License
Classifier: Natural Language :: English
Classifier: Operating System :: POSIX :: Linux
Classifier: Programming Language :: Python :: 3
Classifier: Topic :: Office/Business
Classifier: Topic :: Scientific/Engineering :: Mathematics
Classifier: Topic :: Utilities
